removemd/__init__.py
removemd/core.py
removemd/services/__init__.py
removemd/services/analyzer/check.py
removemd/services/analyzer/inspecter.py
removemd/services/scrubber/remover.py
removemd/services/scrubber/strip.py
removemd/utils/__init__.py
removemd/utils/file_utils.py
removemd-0.1.3.dist-info/licenses/LICENSE
removemd-0.1.3.dist-info/METADATA
removemd-0.1.3.dist-info/WHEEL
removemd-0.1.3.dist-info/entry_points.txt
removemd-0.1.3.dist-info/top_level.txt
removemd-0.1.3.dist-info/RECORD
