Metadata-Version: 2.4
Name: removemd
Version: 0.1.3
Summary: Remove metadata from images, PDFs, Office documents, audio, and video to protect your privacy.
Author-email: Jules Esnault <contact@removemd.com>
License: Apache-2.0
Project-URL: Homepage, https://removemd.com
Project-URL: Repository, https://github.com/Gravyt1/removemd
Project-URL: LinkedIn, https://www.linkedin.com/in/jules-esnault-b84b32373/
Requires-Python: >=3.8
License-File: LICENSE
Requires-Dist: docx==0.2.4
Requires-Dist: ffmpeg-python==0.2.0
Requires-Dist: mutagen==1.47.0
Requires-Dist: openpyxl==3.1.5
Requires-Dist: pillow==11.3.0
Requires-Dist: PyPDF2==3.0.1
Requires-Dist: python-docx==1.2.0
Requires-Dist: python-pptx==1.0.2
Requires-Dist: xlsxwriter==3.2.9
Dynamic: license-file
